Workbook

Sheet Inventory
A1: Product Name | B1: Category | C1: Cost Price | D1: Selling Price | E1: Stock Quantity | F1: Reorder Level | G1: Expiry Date
A2: Besmid Bath Large | D2: 110 | E2: 2
A3: Iman Bath Large | D3: 90 | E3: 1
A4: Makari Bath Large | D4: 80 | E4: 2
A5: Dr. Teals Bath Large | D5: 110 | E5: 1
A6: Kojic Sen Bath Large | D6: 90 | E6: 2
A7: Kojic Sen Soap | D7: 25 | E7: =SUMIF(Purchases!B:B,#REF!,Purchases!D:D)-SUMIF(Sales!B:B,#REF!,Sales!D:D) -> 0
A8: Dove Bath Large | D8: 80 | E8: 1
A9: Nano Bath Large | D9: 90 | E9: 1
A10: Golden Glow Bath Large | D10: 90 | E10: 1
A11: B-Glow Shower Large | D11: 90 | E11: 1
A12: Felce Azzura Bath Large | D12: 70 | E12: 1
A13: Palmolive Bath Large | D13: 80 | E13: 1
A14: fruiser Bath Large | D14: 80 | E14: 3
A15: Style Up Shower Large | D15: 35 | E15: 1
A16: GS 77 shampoo Large | D16: 45 | E16: 2
A17: Gentleman shower Large | D17: 25 | E17: 2
A18: Dr. Teals lotion | B18: Lotion | D18: 120 | E18: 1
A19: Vaseline daily brightening large orig | B19: Lotion | D19: 180 | E19: 1
A20: Vaseline daily brightening medium | B20: Lotion | D20: 150 | E20: =SUMIF(Purchases!B:B,#REF!,Purchases!D:D)-SUMIF(Sales!B:B,#REF!,Sales!D:D) -> 0
A21: Vaseline daily brightening small | B21: Lotion | D21: 65 | E21: =SUMIF(Purchases!B:B,#REF!,Purchases!D:D)-SUMIF(Sales!B:B,#REF!,Sales!D:D) -> 0
A22: Vaseline Lotion | B22: Lotion | D22: 45 | E22: 3
A23: Skin pilar Lotion | B23: Lotion | D23: 120 | E23: 1
A24: Palmers Lotion | B24: Lotion | D24: 120 | E24: 1
A25: Palmers cream large | B25: Cream | D25: 150 | E25: 1
A26: Smooth diamond Lotion large | D26: 130 | E26: 2
A27: Pure Egyptian gold Lotion | D27: 100 | E27: 2
A28: Ellen Beauty lotion | D28: 100 | E28: 1
A29: Palmer’s body oil | D29: 120 | E29: 1
A30: Palmer's skin therapy oil | D30: 200
A31: Cure lala large | D31: 70 | E31: 1
A32: Lumine gold Lotion | D32: 100 | E32: 1
A33: Ensure Shake | D33: 70 | E33: 3
A34: Skin doctor | D34: 90 | E34: =SUMIF(Purchases!B:B,#REF!,Purchases!D:D)-SUMIF(Sales!B:B,#REF!,Sales!D:D) -> 0
A35: Oly Lotion | D35: 280 | E35: =SUMIF(Purchases!B:B,#REF!,Purchases!D:D)-SUMIF(Sales!B:B,#REF!,Sales!D:D) -> 0
A36: Rubee Lotion | D36: 300 | E36: =SUMIF(Purchases!B:B,#REF!,Purchases!D:D)-SUMIF(Sales!B:B,#REF!,Sales!D:D) -> 0
A37: Dove Lotion | D37: 65 | E37: 2
A38: Pure white gold large | D38: 60 | E38: 2
A39: Pure white gold small | D39: 35 | E39: 2
A40: Johnson cotton lot large | D40: 70 | E40: 1
A41: Perly lotion large | D41: 90 | E41: 1
A42: Rapid clair Lotion large | D42: 80 | E42: 1
A43: Elixerlight Lotion large | D43: 65 | E43: 2
A44: Elixerlight Lotion small | D44: 35 | E44: 3
A45: Cocoderm Lotion large | D45: 40 | E45: 2
A46: Cocoderm Lotion medium | D46: 25 | E46: 4
A47: Cocoderm Lotion small | D47: 15 | E47: 2
A48: Kris Lotion Large | D48: 50 | E48: 1
A49: CT+ Lotion large | D49: 60 | E49: =SUMIF(Purchases!B:B,#REF!,Purchases!D:D)-SUMIF(Sales!B:B,#REF!,Sales!D:D) -> 0
A50: Dammy Lotion Large | D50: 40 | E50: =SUMIF(Purchases!B:B,#REF!,Purchases!D:D)-SUMIF(Sales!B:B,#REF!,Sales!D:D) -> 0
A51: CT+ Lotion small | D51: 30 | E51: 4
A52: Dammy Lotion Small | D52: 20 | E52: 1
A53: Mega white Lotion Large | D53: 40 | E53: 1
A54: Mega white Lotion Small | D54: 20 | E54: 2
A55: Beauty clinic Lotion large | D55: 60 | E55: 7
A56: Beauty clinic Lotion small | D56: 35 | E56: 3
A57: Day by day Lotion large | D57: 28 | E57: 1
A58: Day by day Lotion medium | D58: 15 | E58: =SUMIF(Purchases!B:B,#REF!,Purchases!D:D)-SUMIF(Sales!B:B,#REF!,Sales!D:D) -> 0
A59: Day by day Lotion small | D59: 12 | E59: 1
A60: Dream Skin Lotion large | D60: 80 | E60: =SUMIF(Purchases!B:B,#REF!,Purchases!D:D)-SUMIF(Sales!B:B,#REF!,Sales!D:D) -> 0
A61: Dream Skin Lotion small | D61: 45 | E61: 1
A62: Egg Skin lotion large | D62: 45 | E62: 2
A63: Egg Skin lotion small | D63: 0 | E63: =SUMIF(Purchases!B:B,#REF!,Purchases!D:D)-SUMIF(Sales!B:B,#REF!,Sales!D:D) -> 0
A64: Light Up Lotion large | D64: 40 | E64: 3
A65: Light Up Lotion small | D65: 25 | E65: 2
A66: Precious Lotion large | D66: 55 | E66: 1
A67: Precious Lotion small | D67: 30 | E67: =SUMIF(Purchases!B:B,#REF!,Purchases!D:D)-SUMIF(Sales!B:B,#REF!,Sales!D:D) -> 0
A68: Dodo Lotion Large | D68: 50 | E68: =SUMIF(Purchases!B:B,#REF!,Purchases!D:D)-SUMIF(Sales!B:B,#REF!,Sales!D:D) -> 0
A69: Dodo Lotion Small | D69: 27 | E69: 3
A70: 7 days Lotion large | D70: 50 | E70: =SUMIF(Purchases!B:B,#REF!,Purchases!D:D)-SUMIF(Sales!B:B,#REF!,Sales!D:D) -> 0
A71: 7 days Lotion small | D71: 25 | E71: 2
A72: Insta White Lotion large | D72: 35 | E72: 2
A73: Insta White Lotion medium | D73: 25 | E73: 3
A74: Insta White Lotion small | D74: 15 | E74: =SUMIF(Purchases!B:B,#REF!,Purchases!D:D)-SUMIF(Sales!B:B,#REF!,Sales!D:D) -> 0
A75: Caretone Lotion large | D75: 40 | E75: 2
A76: Caretone Lotion small | D76: 20 | E76: 2
A77: White Cat Lotion Small | D77: 15 | E77: 2
A78: DES Lotion large | D78: 50 | E78: 1
A79: DES Lotion medium | D79: 30 | E79: 3
A80: DES Lotion small | D80: 15 | E80: 1
A81: DES shower large | D81: 40 | E81: 1
A82: DES shower small | D82: 20 | E82: =SUMIF(Purchases!B:B,#REF!,Purchases!D:D)-SUMIF(Sales!B:B,#REF!,Sales!D:D) -> 0
A83: Nivea RN Lotion | D83: 65 | E83: 3
A84: Nivea Cocoa Lotion | D84: 65 | E84: 4
A85: Nivea PR Lotion | D85: 65 | E85: =SUMIF(Purchases!B:B,#REF!,Purchases!D:D)-SUMIF(Sales!B:B,#REF!,Sales!D:D) -> 0
A86: Nivea Q10 Lotion | D86: 75 | E86: 3
A87: Nivea RB lotion | D87: 75 | E87: 2
A88: Stretch mark cream | D88: 50 | E88: 2
A89: Bio Oil medium | D89: 50 | E89: =SUMIF(Purchases!B:B,#REF!,Purchases!D:D)-SUMIF(Sales!B:B,#REF!,Sales!D:D) -> 0
A90: Rose hand cream large | D90: 50 | E90: 1
A91: Strawberry hand cream small | D91: 15 | E91: =SUMIF(Purchases!B:B,#REF!,Purchases!D:D)-SUMIF(Sales!B:B,#REF!,Sales!D:D) -> 0
A92: Amis cream Medium | D92: 80 | E92: 1
A93: Amis oil | D93: 65 | E93: 1
A94: Vaseline VC oil | D94: 140 | E94: 1
A95: Easy glow Lotion | D95: 120 | E95: 1
A96: Johnson Baby oil medium | D96: 80 | E96: 1
A97: Johnson Baby oil small | D97: 50 | E97: =SUMIF(Purchases!B:B,#REF!,Purchases!D:D)-SUMIF(Sales!B:B,#REF!,Sales!D:D) -> 0
A98: Teen's and Kids body millk | D98: 80 | E98: =SUMIF(Purchases!B:B,#REF!,Purchases!D:D)-SUMIF(Sales!B:B,#REF!,Sales!D:D) -> 0
A99: Kleencarrot Lotion | D99: 100 | E99: 1
A100: Pure no marks facial | D100: 55 | E100: 3
...

Sheet Sales
A1: Date | B1: Product ID | C1: Product Name | D1: Quantity Sold | E1: Unit Price | F1: Total Price | G1: Payment Method
A2: 46127 | B2: Besmid Bath Large | C2: =IFERROR(VLOOKUP(B2,Inventory!A:G,2,FALSE),"") -> 0 | D2: 1 | E2: =IFERROR(VLOOKUP(B2,Inventory!A:G,5,FALSE),"") -> 2 | F2: =D2*E2 -> 2
A3: 46127 | B3: Mega white Lotion large | C3: =IFERROR(VLOOKUP(B3,Inventory!A:G,2,FALSE),"") -> 0 | D3: 2 | E3: =IFERROR(VLOOKUP(B3,Inventory!A:G,5,FALSE),"") -> 1 | F3: =D3*E3 -> 2
A4: 46127 | B4: P1 | C4: =IFERROR(VLOOKUP(B4,Inventory!A:G,2,FALSE),"") | D4: 2 | E4: =IFERROR(VLOOKUP(B4,Inventory!A:G,5,FALSE),"") | F4: =D4*E4 -> #VALUE!
C5: =IFERROR(VLOOKUP(B5,Inventory!A:G,2,FALSE),"") | E5: =IFERROR(VLOOKUP(B5,Inventory!A:G,5,FALSE),"") | F5: =D5*E5 -> #VALUE!
C6: =IFERROR(VLOOKUP(B6,Inventory!A:G,2,FALSE),"") | E6: =IFERROR(VLOOKUP(B6,Inventory!A:G,5,FALSE),"") | F6: =D6*E6 -> #VALUE!
C7: =IFERROR(VLOOKUP(B7,Inventory!A:G,2,FALSE),"") | E7: =IFERROR(VLOOKUP(B7,Inventory!A:G,5,FALSE),"") | F7: =D7*E7 -> #VALUE!
C8: =IFERROR(VLOOKUP(B8,Inventory!A:G,2,FALSE),"") | E8: =IFERROR(VLOOKUP(B8,Inventory!A:G,5,FALSE),"") | F8: =D8*E8 -> #VALUE!
C9: =IFERROR(VLOOKUP(B9,Inventory!A:G,2,FALSE),"") | E9: =IFERROR(VLOOKUP(B9,Inventory!A:G,5,FALSE),"") | F9: =D9*E9 -> #VALUE!
C10: =IFERROR(VLOOKUP(B10,Inventory!A:G,2,FALSE),"") | E10: =IFERROR(VLOOKUP(B10,Inventory!A:G,5,FALSE),"") | F10: =D10*E10 -> #VALUE!
C11: =IFERROR(VLOOKUP(B11,Inventory!A:G,2,FALSE),"") | E11: =IFERROR(VLOOKUP(B11,Inventory!A:G,5,FALSE),"") | F11: =D11*E11 -> #VALUE!
C12: =IFERROR(VLOOKUP(B12,Inventory!A:G,2,FALSE),"") | E12: =IFERROR(VLOOKUP(B12,Inventory!A:G,5,FALSE),"") | F12: =D12*E12 -> #VALUE!
C13: =IFERROR(VLOOKUP(B13,Inventory!A:G,2,FALSE),"") | E13: =IFERROR(VLOOKUP(B13,Inventory!A:G,5,FALSE),"") | F13: =D13*E13 -> #VALUE!
C14: =IFERROR(VLOOKUP(B14,Inventory!A:G,2,FALSE),"") | E14: =IFERROR(VLOOKUP(B14,Inventory!A:G,5,FALSE),"") | F14: =D14*E14 -> #VALUE!
C15: =IFERROR(VLOOKUP(B15,Inventory!A:G,2,FALSE),"") | E15: =IFERROR(VLOOKUP(B15,Inventory!A:G,5,FALSE),"") | F15: =D15*E15 -> #VALUE!
C16: =IFERROR(VLOOKUP(B16,Inventory!A:G,2,FALSE),"") | E16: =IFERROR(VLOOKUP(B16,Inventory!A:G,5,FALSE),"") | F16: =D16*E16 -> #VALUE!
... C499: =IFERROR(VLOOKUP(B499,Inventory!A:G,2,FALSE),"") | E499: =IFERROR(VLOOKUP(B499,Inventory!A:G,5,FALSE),"") | F499: =D499*E499 -> #VALUE!

Sheet Purchases
A1: Date | B1: Product ID | C1: Product Name | D1: Quantity | E1: Cost Price | F1: Total Cost
A2: 46127 | B2: P1 | C2: =IFERROR(VLOOKUP(B2,Inventory!A:G,2,FALSE),"") | D2: 20 | E2: =IFERROR(VLOOKUP(B2,Inventory!A:G,4,FALSE),"") | F2: =D2*E2 -> #VALUE!
C3: =IFERROR(VLOOKUP(B3,Inventory!A:G,2,FALSE),"") | E3: =IFERROR(VLOOKUP(B3,Inventory!A:G,4,FALSE),"") | F3: =D3*E3 -> #VALUE!
C4: =IFERROR(VLOOKUP(B4,Inventory!A:G,2,FALSE),"") | E4: =IFERROR(VLOOKUP(B4,Inventory!A:G,4,FALSE),"") | F4: =D4*E4 -> #VALUE!
C5: =IFERROR(VLOOKUP(B5,Inventory!A:G,2,FALSE),"") | E5: =IFERROR(VLOOKUP(B5,Inventory!A:G,4,FALSE),"") | F5: =D5*E5 -> #VALUE!
C6: =IFERROR(VLOOKUP(B6,Inventory!A:G,2,FALSE),"") | E6: =IFERROR(VLOOKUP(B6,Inventory!A:G,4,FALSE),"") | F6: =D6*E6 -> #VALUE!
C7: =IFERROR(VLOOKUP(B7,Inventory!A:G,2,FALSE),"") | E7: =IFERROR(VLOOKUP(B7,Inventory!A:G,4,FALSE),"") | F7: =D7*E7 -> #VALUE!
C8: =IFERROR(VLOOKUP(B8,Inventory!A:G,2,FALSE),"") | E8: =IFERROR(VLOOKUP(B8,Inventory!A:G,4,FALSE),"") | F8: =D8*E8 -> #VALUE!
C9: =IFERROR(VLOOKUP(B9,Inventory!A:G,2,FALSE),"") | E9: =IFERROR(VLOOKUP(B9,Inventory!A:G,4,FALSE),"") | F9: =D9*E9 -> #VALUE!
C10: =IFERROR(VLOOKUP(B10,Inventory!A:G,2,FALSE),"") | E10: =IFERROR(VLOOKUP(B10,Inventory!A:G,4,FALSE),"") | F10: =D10*E10 -> #VALUE!
C11: =IFERROR(VLOOKUP(B11,Inventory!A:G,2,FALSE),"") | E11: =IFERROR(VLOOKUP(B11,Inventory!A:G,4,FALSE),"") | F11: =D11*E11 -> #VALUE!
C12: =IFERROR(VLOOKUP(B12,Inventory!A:G,2,FALSE),"") | E12: =IFERROR(VLOOKUP(B12,Inventory!A:G,4,FALSE),"") | F12: =D12*E12 -> #VALUE!
C13: =IFERROR(VLOOKUP(B13,Inventory!A:G,2,FALSE),"") | E13: =IFERROR(VLOOKUP(B13,Inventory!A:G,4,FALSE),"") | F13: =D13*E13 -> #VALUE!
C14: =IFERROR(VLOOKUP(B14,Inventory!A:G,2,FALSE),"") | E14: =IFERROR(VLOOKUP(B14,Inventory!A:G,4,FALSE),"") | F14: =D14*E14 -> #VALUE!
... C499: =IFERROR(VLOOKUP(B499,Inventory!A:G,2,FALSE),"") | E499: =IFERROR(VLOOKUP(B499,Inventory!A:G,4,FALSE),"") | F499: =D499*E499 -> #VALUE!

Sheet Expenses
A1: Date | B1: Description | C1: Amount | D1: Paid By

Sheet Dashboard
A1: PREMIUM COSMETICS SHOP DASHBOARD
A3: Total Sales: | B3: =SUM(Sales!F2:F500) -> #VALUE!
A4: Total Expenses: | B4: =SUM(Expenses!C2:C500) -> 0
A5: Net Profit: | B5: =B3-B4 -> #VALUE!
A7: Top Section: Monthly Sales Chart Below
A8: April

Sheet Monthly Analysis
A1: Month | B1: Sales
A2: Jan | B2: =SUM(Sales!F:F) -> #VALUE!
A3: Feb | B3: =SUM(Sales!F:F) -> #VALUE!
A4: Mar | B4: =SUM(Sales!F:F) -> #VALUE!
A5: Apr | B5: =SUM(Sales!F:F) -> #VALUE!
A6: May | B6: =SUM(Sales!F:F) -> #VALUE!
A7: Jun | B7: =SUM(Sales!F:F) -> #VALUE!
A8: Jul | B8: =SUM(Sales!F:F) -> #VALUE!
A9: Aug | B9: =SUM(Sales!F:F) -> #VALUE!
A10: Sep | B10: =SUM(Sales!F:F) -> #VALUE!
A11: Oct | B11: =SUM(Sales!F:F) -> #VALUE!
A12: Nov | B12: =SUM(Sales!F:F) -> #VALUE!
A13: Dec | B13: =SUM(Sales!F:F) -> #VALUE!

Sheet POS
A1: SIMPLE POS INTERFACE
A3: Product ID | B3: P1
A4: Quantity | B4: 2
A5: Auto Price | B5: =IFERROR(VLOOKUP(B3,Inventory!A:G,5,FALSE),"")
A6: Total | B6: =B4*B5 -> #VALUE!
